[
  {
    "title": "2011",
    "url": "https://www.who.int/emergencies/disease-outbreak-news/item/2011_12_21-en",
    "date": "2011-12-21",
    "category": "Disease Outbreak News",
    "scraped_at": "2026-01-29T10:04:00.314017"
  },
  {
    "title": "2011",
    "url": "https://www.who.int/emergencies/disease-outbreak-news/item/2011_12_15-en",
    "date": "2011-12-15",
    "category": "Disease Outbreak News",
    "scraped_at": "2026-01-29T10:04:00.314168"
  },
  {
    "title": "2011 - Senegal",
    "url": "https://www.who.int/emergencies/disease-outbreak-news/item/2011_12_01-en",
    "date": "2011-12-01",
    "category": "Disease Outbreak News",
    "scraped_at": "2026-01-29T10:04:00.314313"
  },
  {
    "title": "2011",
    "url": "https://www.who.int/emergencies/disease-outbreak-news/item/2011_11_29-en",
    "date": "2011-11-29",
    "category": "Disease Outbreak News",
    "scraped_at": "2026-01-29T10:04:00.314466"
  },
  {
    "title": "2011",
    "url": "https://www.who.int/emergencies/disease-outbreak-news/item/2011_11_24-en",
    "date": "2011-11-24",
    "category": "Disease Outbreak News",
    "scraped_at": "2026-01-29T10:04:00.314613"
  },
  {
    "title": "2011 - Indonesia",
    "url": "https://www.who.int/emergencies/disease-outbreak-news/item/2011_11_15-en",
    "date": "2011-11-15",
    "category": "Disease Outbreak News",
    "scraped_at": "2026-01-29T10:04:00.314758"
  },
  {
    "title": "2011 - Nigeria",
    "url": "https://www.who.int/emergencies/disease-outbreak-news/item/2011_11_11-en",
    "date": "2011-11-11",
    "category": "Disease Outbreak News",
    "scraped_at": "2026-01-29T10:04:00.314903"
  },
  {
    "title": "2011 - Egypt",
    "url": "https://www.who.int/emergencies/disease-outbreak-news/item/2011_11_02-en",
    "date": "2011-11-02",
    "category": "Disease Outbreak News",
    "scraped_at": "2026-01-29T10:04:00.315048"
  },
  {
    "title": "2011 - Indonesia",
    "url": "https://www.who.int/emergencies/disease-outbreak-news/item/2011_10_26-en",
    "date": "2011-10-26",
    "category": "Disease Outbreak News",
    "scraped_at": "2026-01-29T10:04:00.315199"
  },
  {
    "title": "2011 - Indonesia",
    "url": "https://www.who.int/emergencies/disease-outbreak-news/item/2011_10_10-en",
    "date": "2011-10-10",
    "category": "Disease Outbreak News",
    "scraped_at": "2026-01-29T10:04:00.315349"
  },
  {
    "title": "2011 - France",
    "url": "https://www.who.int/emergencies/disease-outbreak-news/item/2011_10_07-en",
    "date": "2011-10-07",
    "category": "Disease Outbreak News",
    "scraped_at": "2026-01-29T10:04:00.315504"
  },
  {
    "title": "2011",
    "url": "https://www.who.int/emergencies/disease-outbreak-news/item/2011_09_20-en",
    "date": "2011-09-20",
    "category": "Disease Outbreak News",
    "scraped_at": "2026-01-29T10:04:00.315661"
  },
  {
    "title": "2011 - China",
    "url": "https://www.who.int/emergencies/disease-outbreak-news/item/2011_09_01-en",
    "date": "2011-09-01",
    "category": "Disease Outbreak News",
    "scraped_at": "2026-01-29T10:04:00.315805"
  },
  {
    "title": "2011 - Cambodia",
    "url": "https://www.who.int/emergencies/disease-outbreak-news/item/2011_08_19-en",
    "date": "2011-08-19",
    "category": "Disease Outbreak News",
    "scraped_at": "2026-01-29T10:04:00.315953"
  },
  {
    "title": "2011",
    "url": "https://www.who.int/emergencies/disease-outbreak-news/item/2011_08_16-en",
    "date": "2011-08-16",
    "category": "Disease Outbreak News",
    "scraped_at": "2026-01-29T10:04:06.542172"
  },
  {
    "title": "2011 - Congo",
    "url": "https://www.who.int/emergencies/disease-outbreak-news/item/2011_08_15-en",
    "date": "2011-08-15",
    "category": "Disease Outbreak News",
    "scraped_at": "2026-01-29T10:04:06.542342"
  },
  {
    "title": "2011 - Egypt",
    "url": "https://www.who.int/emergencies/disease-outbreak-news/item/2011_08_09-en",
    "date": "2011-08-09",
    "category": "Disease Outbreak News",
    "scraped_at": "2026-01-29T10:04:06.542496"
  },
  {
    "title": "2011 - Cambodia",
    "url": "https://www.who.int/emergencies/disease-outbreak-news/item/2011_08_02-en",
    "date": "2011-08-02",
    "category": "Disease Outbreak News",
    "scraped_at": "2026-01-29T10:04:06.542653"
  },
  {
    "title": "2011 - Congo",
    "url": "https://www.who.int/emergencies/disease-outbreak-news/item/2011_07_22-en",
    "date": "2011-07-22",
    "category": "Disease Outbreak News",
    "scraped_at": "2026-01-29T10:04:06.542835"
  },
  {
    "title": "2011 - Pakistan",
    "url": "https://www.who.int/emergencies/disease-outbreak-news/item/2011_07_07-en",
    "date": "2011-07-07",
    "category": "Disease Outbreak News",
    "scraped_at": "2026-01-29T10:04:06.542984"
  },
  {
    "title": "2011 - Egypt",
    "url": "https://www.who.int/emergencies/disease-outbreak-news/item/2011_06_22-en",
    "date": "2011-06-22",
    "category": "Disease Outbreak News",
    "scraped_at": "2026-01-29T10:04:06.543127"
  },
  {
    "title": "2011 - Egypt",
    "url": "https://www.who.int/emergencies/disease-outbreak-news/item/2011_06_16-en",
    "date": "2011-06-16",
    "category": "Disease Outbreak News",
    "scraped_at": "2026-01-29T10:04:06.543271"
  },
  {
    "title": "Influenza A (H5N1) virus - Cambodia",
    "url": "https://www.who.int/emergencies/disease-outbreak-news/item/2011DON036",
    "date": "2011-06-10",
    "category": "Disease Outbreak News",
    "scraped_at": "2026-01-29T10:04:06.543414"
  },
  {
    "title": "2011 - Chad",
    "url": "https://www.who.int/emergencies/disease-outbreak-news/item/2011_06_10a-en",
    "date": "2011-06-10",
    "category": "Disease Outbreak News",
    "scraped_at": "2026-01-29T10:04:06.543566"
  },
  {
    "title": "2011 - Indonesia",
    "url": "https://www.who.int/emergencies/disease-outbreak-news/item/2011_06_03-en",
    "date": "2011-06-03",
    "category": "Disease Outbreak News",
    "scraped_at": "2026-01-29T10:04:06.543713"
  },
  {
    "title": "2011 - Germany",
    "url": "https://www.who.int/emergencies/disease-outbreak-news/item/2011_06_02-en",
    "date": "2011-06-02",
    "category": "Disease Outbreak News",
    "scraped_at": "2026-01-29T10:04:06.543864"
  },
  {
    "title": "2011 - Egypt",
    "url": "https://www.who.int/emergencies/disease-outbreak-news/item/2011_06_01-en",
    "date": "2011-06-01",
    "category": "Disease Outbreak News",
    "scraped_at": "2026-01-29T10:04:06.544007"
  },
  {
    "title": "2011 - Germany",
    "url": "https://www.who.int/emergencies/disease-outbreak-news/item/2011_05_27-en",
    "date": "2011-05-27",
    "category": "Disease Outbreak News",
    "scraped_at": "2026-01-29T10:04:06.544150"
  },
  {
    "title": "2011 - Uganda",
    "url": "https://www.who.int/emergencies/disease-outbreak-news/item/2011_05_18-en",
    "date": "2011-05-18",
    "category": "Disease Outbreak News",
    "scraped_at": "2026-01-29T10:04:06.544292"
  },
  {
    "title": "2011 - Indonesia",
    "url": "https://www.who.int/emergencies/disease-outbreak-news/item/2011_05_13-en",
    "date": "2011-05-13",
    "category": "Disease Outbreak News",
    "scraped_at": "2026-01-29T10:04:06.544438"
  },
  {
    "title": "Measles - Region of Europe",
    "url": "https://www.who.int/emergencies/disease-outbreak-news/item/2011DON035",
    "date": "2011-04-21",
    "category": "Disease Outbreak News",
    "scraped_at": "2026-01-29T10:04:06.544587"
  },
  {
    "title": "2011 - Egypt",
    "url": "https://www.who.int/emergencies/disease-outbreak-news/item/2011_04_21d-en",
    "date": "2011-04-21",
    "category": "Disease Outbreak News",
    "scraped_at": "2026-01-29T10:04:06.544731"
  },
  {
    "title": "2011 - Cambodia",
    "url": "https://www.who.int/emergencies/disease-outbreak-news/item/2011_04_21c-en",
    "date": "2011-04-21",
    "category": "Disease Outbreak News",
    "scraped_at": "2026-01-29T10:04:06.544875"
  },
  {
    "title": "2011 - Nigeria",
    "url": "https://www.who.int/emergencies/disease-outbreak-news/item/2011_04_21a-en",
    "date": "2011-04-21",
    "category": "Disease Outbreak News",
    "scraped_at": "2026-01-29T10:04:06.545018"
  },
  {
    "title": "Influenza A (H5N1) virus - Egypt",
    "url": "https://www.who.int/emergencies/disease-outbreak-news/item/2011DON034",
    "date": "2011-04-11",
    "category": "Disease Outbreak News",
    "scraped_at": "2026-01-29T10:04:06.545161"
  },
  {
    "title": "2011 - Bangladesh",
    "url": "https://www.who.int/emergencies/disease-outbreak-news/item/2011_04_11a-en",
    "date": "2011-04-11",
    "category": "Disease Outbreak News",
    "scraped_at": "2026-01-29T10:04:06.545305"
  },
  {
    "title": "2011 - Cambodia",
    "url": "https://www.who.int/emergencies/disease-outbreak-news/item/2011_04_11b-en",
    "date": "2011-04-11",
    "category": "Disease Outbreak News",
    "scraped_at": "2026-01-29T10:04:06.545450"
  },
  {
    "title": "2011 - Egypt",
    "url": "https://www.who.int/emergencies/disease-outbreak-news/item/2011_04_06-en",
    "date": "2011-04-06",
    "category": "Disease Outbreak News",
    "scraped_at": "2026-01-29T10:04:06.545598"
  },
  {
    "title": "2011 - Indonesia",
    "url": "https://www.who.int/emergencies/disease-outbreak-news/item/2011_04_01-en",
    "date": "2011-04-01",
    "category": "Disease Outbreak News",
    "scraped_at": "2026-01-29T10:04:06.545743"
  },
  {
    "title": "2011 - Egypt",
    "url": "https://www.who.int/emergencies/disease-outbreak-news/item/2011_03_29-en",
    "date": "2011-03-29",
    "category": "Disease Outbreak News",
    "scraped_at": "2026-01-29T10:04:06.545893"
  },
  {
    "title": "2011 - Indonesia",
    "url": "https://www.who.int/emergencies/disease-outbreak-news/item/2011_03_25-en",
    "date": "2011-03-25",
    "category": "Disease Outbreak News",
    "scraped_at": "2026-01-29T10:04:06.546036"
  },
  {
    "title": "2011 - Bangladesh",
    "url": "https://www.who.int/emergencies/disease-outbreak-news/item/2011_03_16-en",
    "date": "2011-03-16",
    "category": "Disease Outbreak News",
    "scraped_at": "2026-01-29T10:04:06.546180"
  },
  {
    "title": "2011 - Egypt",
    "url": "https://www.who.int/emergencies/disease-outbreak-news/item/2011_03_15-en",
    "date": "2011-03-15",
    "category": "Disease Outbreak News",
    "scraped_at": "2026-01-29T10:04:12.771995"
  },
  {
    "title": "2011 - Indonesia",
    "url": "https://www.who.int/emergencies/disease-outbreak-news/item/2011_03_14-en",
    "date": "2011-03-14",
    "category": "Disease Outbreak News",
    "scraped_at": "2026-01-29T10:04:12.772162"
  },
  {
    "title": "2011 - Sierra Leone",
    "url": "https://www.who.int/emergencies/disease-outbreak-news/item/2011_03_11-en",
    "date": "2011-03-11",
    "category": "Disease Outbreak News",
    "scraped_at": "2026-01-29T10:04:12.772309"
  },
  {
    "title": "2011 - Egypt",
    "url": "https://www.who.int/emergencies/disease-outbreak-news/item/2011_03_10-en",
    "date": "2011-03-10",
    "category": "Disease Outbreak News",
    "scraped_at": "2026-01-29T10:04:12.772453"
  },
  {
    "title": "2011 - Chad",
    "url": "https://www.who.int/emergencies/disease-outbreak-news/item/2011_03_08-en",
    "date": "2011-03-08",
    "category": "Disease Outbreak News",
    "scraped_at": "2026-01-29T10:04:12.772596"
  },
  {
    "title": "2011 - Egypt",
    "url": "https://www.who.int/emergencies/disease-outbreak-news/item/2011_03_07-en",
    "date": "2011-03-07",
    "category": "Disease Outbreak News",
    "scraped_at": "2026-01-29T10:04:12.772746"
  },
  {
    "title": "2011 - Indonesia",
    "url": "https://www.who.int/emergencies/disease-outbreak-news/item/2011_03_02-en",
    "date": "2011-03-02",
    "category": "Disease Outbreak News",
    "scraped_at": "2026-01-29T10:04:12.772897"
  },
  {
    "title": "2011 - Egypt",
    "url": "https://www.who.int/emergencies/disease-outbreak-news/item/2011_02_28-en",
    "date": "2011-02-28",
    "category": "Disease Outbreak News",
    "scraped_at": "2026-01-29T10:04:12.773041"
  },
  {
    "title": "2011 - Cambodia",
    "url": "https://www.who.int/emergencies/disease-outbreak-news/item/2011_02_25-en",
    "date": "2011-02-25",
    "category": "Disease Outbreak News",
    "scraped_at": "2026-01-29T10:04:12.773188"
  },
  {
    "title": "2011 - Cambodia",
    "url": "https://www.who.int/emergencies/disease-outbreak-news/item/2011_02_09-en",
    "date": "2011-02-09",
    "category": "Disease Outbreak News",
    "scraped_at": "2026-01-29T10:04:12.773333"
  },
  {
    "title": "2011 - Egypt",
    "url": "https://www.who.int/emergencies/disease-outbreak-news/item/2011_02_02-en",
    "date": "2011-02-02",
    "category": "Disease Outbreak News",
    "scraped_at": "2026-01-29T10:04:12.773482"
  },
  {
    "title": "2011",
    "url": "https://www.who.int/emergencies/disease-outbreak-news/item/2011_02_01-en",
    "date": "2011-02-01",
    "category": "Disease Outbreak News",
    "scraped_at": "2026-01-29T10:04:12.773633"
  },
  {
    "title": "2011",
    "url": "https://www.who.int/emergencies/disease-outbreak-news/item/2011_01_25-en",
    "date": "2011-01-25",
    "category": "Disease Outbreak News",
    "scraped_at": "2026-01-29T10:04:12.773779"
  },
  {
    "title": "2011 - Egypt",
    "url": "https://www.who.int/emergencies/disease-outbreak-news/item/2011_01_20-en",
    "date": "2011-01-20",
    "category": "Disease Outbreak News",
    "scraped_at": "2026-01-29T10:04:12.773922"
  },
  {
    "title": "2011 - Uganda",
    "url": "https://www.who.int/emergencies/disease-outbreak-news/item/2011_01_19-en",
    "date": "2011-01-19",
    "category": "Disease Outbreak News",
    "scraped_at": "2026-01-29T10:04:12.774072"
  },
  {
    "title": "2011 - Egypt",
    "url": "https://www.who.int/emergencies/disease-outbreak-news/item/2011_01_12-en",
    "date": "2011-01-13",
    "category": "Disease Outbreak News",
    "scraped_at": "2026-01-29T10:04:12.774216"
  },
  {
    "title": "2011 - Egypt",
    "url": "https://www.who.int/emergencies/disease-outbreak-news/item/2011_01_05-en",
    "date": "2011-01-05",
    "category": "Disease Outbreak News",
    "scraped_at": "2026-01-29T10:04:12.774367"
  }
]